AUTHORS.rst
CONTRIBUTING.rst
HISTORY.rst
LICENSE
MANIFEST.in
README.rst
setup.cfg
setup.py
docs/Makefile
docs/authors.rst
docs/conf.py
docs/contributing.rst
docs/history.rst
docs/index.rst
docs/installation.rst
docs/make.bat
docs/readme.rst
docs/usage.rst
faster_parser/__init__.py
faster_parser/faster_parse.py
faster_parser.egg-info/PKG-INFO
faster_parser.egg-info/SOURCES.txt
faster_parser.egg-info/dependency_links.txt
faster_parser.egg-info/not-zip-safe
faster_parser.egg-info/requires.txt
faster_parser.egg-info/top_level.txt
tests/__init__.py
tests/test_faster_parser.py