Metadata-Version: 2.1
Name: faster-parser
Version: 0.1.0
Summary: Util function to process data concurrently
Home-page: https://github.com/paul-armstrong-dev/faster_parser
Author: Paul Armstrong
Author-email: paul.armstrong211@gmail.com
License: MIT license
Keywords: faster_parser
Platform: UNKNOWN
Classifier: Development Status :: 2 - Pre-Alpha
Classifier: Intended Audience :: Developers
Classifier: License :: OSI Approved :: MIT License
Classifier: Natural Language :: English
Classifier: Programming Language :: Python :: 3
Classifier: Programming Language :: Python :: 3.6
Classifier: Programming Language :: Python :: 3.7
Classifier: Programming Language :: Python :: 3.8
Requires-Python: >=3.6
License-File: LICENSE
License-File: AUTHORS.rst
